LICENSE
README.md
setup.py
metacontrollers/__init__.py
metacontrollers.egg-info/PKG-INFO
metacontrollers.egg-info/SOURCES.txt
metacontrollers.egg-info/dependency_links.txt
metacontrollers.egg-info/top_level.txt
metacontrollers.egg-info/zip-safe
metacontrollers/internal/__init__.py
metacontrollers/internal/exceptions.py
metacontrollers/internal/interface.py
metacontrollers/internal/method_inspector.py
metacontrollers/internal/method_invocation.py
metacontrollers/internal/namespace.py
metacontrollers/internal/classes/__init__.py
metacontrollers/internal/classes/_base.py
metacontrollers/internal/classes/do.py
metacontrollers/internal/classes/do_all.py
metacontrollers/internal/classes/do_k.py
metacontrollers/internal/classes/do_one.py
test/test_combinations_args_do_all.py
test/test_combinations_args_do_k.py
test/test_combinations_args_do_one.py
test/test_combinations_do_all copy.py
test/test_combinations_do_all.py
test/test_combinations_do_k.py
test/test_combinations_do_one.py
test/test_inspectors.py
test/test_methods.py
test/test_smoke_do.py
test/test_smoke_do_all.py
test/test_smoke_do_k.py
test/test_smoke_do_one.py