Metadata-Version: 2.1
Name: metacontrollers
Version: 0.1.2
Summary: A Python library for decoupling logic, modeling dynamic systems, and writing more declarative software.
Home-page: https://github.com/nsspencer/MetaControllers
Author: Nathan Spencer
Author-email: nathanss1997@gmail.com
License: BSD 3-Clause
Platform: UNKNOWN
Classifier: Programming Language :: Python :: 3
Classifier: License :: OSI Approved :: BSD License
Classifier: Operating System :: OS Independent
Requires-Python: >=3.8
License-File: LICENSE
